llama_index/llms/premai/__init__.py
llama_index/llms/premai/base.py
llama_index/llms/premai/utils.py
llama_index_llms_premai-0.4.1.dist-info/METADATA
llama_index_llms_premai-0.4.1.dist-info/WHEEL
llama_index_llms_premai-0.4.1.dist-info/licenses/LICENSE
llama_index_llms_premai-0.4.1.dist-info/RECORD
